{"3037":{"call":329,"put":47},"2330":{"call":1173,"put":330},"2454":{"call":698,"put":59},"2308":{"call":409,"put":84},"2368":{"call":340,"put":47},"3665":{"call":347,"put":22},"8046":{"call":236,"put":43},"2317":{"call":729,"put":96},"3008":{"call":252,"put":10},"2327":{"call":344,"put":52},"3661":{"call":637,"put":46},"2449":{"call":317,"put":17},"6805":{"call":262,"put":17},"2357":{"call":73,"put":1},"2383":{"call":264,"put":46},"3017":{"call":603,"put":61},"2313":{"call":367,"put":47},"2345":{"call":402,"put":62},"3036":{"call":64,"put":0},"3653":{"call":40,"put":7},"3711":{"call":268,"put":15},"6669":{"call":561,"put":66},"2404":{"call":270,"put":19},"6515":{"call":45,"put":2},"3443":{"call":206,"put":20},"6191":{"call":135,"put":11},"6415":{"call":164,"put":2},"3376":{"call":110,"put":6},"2303":{"call":276,"put":18},"8996":{"call":4,"put":0},"8210":{"call":206,"put":18},"2002":{"call":52,"put":0},"2481":{"call":175,"put":9},"2337":{"call":193,"put":47},"1590":{"call":52,"put":0},"8150":{"call":167,"put":5},"2439":{"call":27,"put":0},"1319":{"call":20,"put":0}}